andreani/__init__.py
andreani/core/__init__.py
andreani/core/api.py
andreani/core/constants.py
andreani/core/encoders.py
andreani/core/exceptions.py
andreani/core/serializers.py
andreani/core/utils.py
tests/__init__.py
tests/conftest.py
tests/test_api.py
andreani-1.0.0.dist-info/LICENSE
andreani-1.0.0.dist-info/METADATA
andreani-1.0.0.dist-info/WHEEL
andreani-1.0.0.dist-info/top_level.txt
andreani-1.0.0.dist-info/RECORD
