Metadata-Version: 2.1
Name: andreani
Version: 1.0.0
Summary: Andreani SDK for python
Home-page: https://github.com/juanpsenn/andreani
Author: Juan Pablo Senn
Author-email: juanpsenn@gmail.com
License: MIT
Project-URL: Issue Tracker, https://github.com/juanpsenn/andreani/issues
Classifier: Intended Audience :: Developers
Classifier: License :: OSI Approved :: MIT License
Classifier: Operating System :: OS Independent
Classifier: Programming Language :: Python :: 3
Classifier: Programming Language :: Python :: 3.7
Classifier: Programming Language :: Python :: 3.8
Classifier: Programming Language :: Python :: 3.9
Classifier: Programming Language :: Python :: 3.10
Classifier: Topic :: Software Development :: Libraries :: Python Modules
License-File: LICENSE
Requires-Dist: requests (>=2.28.1)
